android_emulator
helper
runner
settings_manager
