Metadata-Version: 2.1
Name: asim-select
Version: 0.2.0
Summary: 
